s3reqs/__init__.py
s3reqs/cli.py
s3reqs/utils.py
s3reqs-0.4.0a0.dist-info/METADATA
s3reqs-0.4.0a0.dist-info/RECORD
s3reqs-0.4.0a0.dist-info/WHEEL
s3reqs-0.4.0a0.dist-info/entry_points.txt
s3reqs-0.4.0a0.dist-info/top_level.txt
